README.rst
setup.py
progressindicator/__init__.py
progressindicator/base.py
progressindicator/core.py
progressindicator/extensions.py
progressindicator/providers.py
progressindicator/tags.py
progressindicator.egg-info/PKG-INFO
progressindicator.egg-info/SOURCES.txt
progressindicator.egg-info/dependency_links.txt
progressindicator.egg-info/top_level.txt