Metadata-Version: 1.1
Name: progressindicator
Version: 0.1.2
Summary: Utility package for displaying a Progress bar.
Home-page: https://github.com/pri22296/progressindicator
Author: Priyam Singh
Author-email: priyamsingh.22296@gmail.com
License: MIT
Download-URL: https://github.com/pri22296/progressindicator/tarball/0.1.2
Platform: UNKNOWN
Classifier: Development Status :: 3 - Alpha
Classifier: Environment :: Console
Classifier: Intended Audience :: Developers
Classifier: License :: OSI Approved :: MIT License
Classifier: Programming Language :: Python
Classifier: Programming Language :: Python :: 3.5
